.Rbuildignore
.babelrc
.eslintignore
.eslintrc
.gitignore
.npmignore
.prettierrc
.pylintrc
CONTRIBUTING.md
DESCRIPTION
LICENSE
MANIFEST.in
NAMESPACE
PUBLISH.md
README.md
_validate_init.py
build.sh
deploy.sh
index.html
package-lock.json
package.json
pytest.ini
requirements.txt
review_checklist.md
setup.py
usage.py
webpack.config.js
webpack.serve.config.js
.idea/dash_ace.iml
.idea/misc.xml
.idea/modules.xml
.idea/vcs.xml
.idea/inspectionProfiles/profiles_settings.xml
R/dashAceEditor.R
R/internal.R
inst/deps/my_dash_ace.min.js
inst/deps/my_dash_ace.min.js.map
man/aceEditor.Rd
man/dashAceEditor.Rd
my_dash_ace/DashAceEditor.py
my_dash_ace/__init__.py
my_dash_ace/_imports_.py
my_dash_ace/metadata.json
my_dash_ace/my_dash_ace.min.js
my_dash_ace/my_dash_ace.min.js.map
my_dash_ace/package-info.json
my_dash_ace.egg-info/PKG-INFO
my_dash_ace.egg-info/SOURCES.txt
my_dash_ace.egg-info/dependency_links.txt
my_dash_ace.egg-info/top_level.txt
src/demo/App.js
src/demo/index.js
src/lib/index.js
src/lib/components/CustomPythonMode.js
src/lib/components/DashAceEditor.react.js
src/lib/components/diff_editor.css
tests/__init__.py
tests/requirements.txt
tests/test_usage.py