Metadata-Version: 2.1
Name: my-dash-ace
Version: 0.0.7
Summary: Dash Ace Editor Component
Home-page: https://github.com/bailaohe/my-dash-ace
Author: xu miao <xu@reasoned.ai>
Author-email: xu@reasoned.ai
License: MIT
Platform: UNKNOWN
Classifier: Framework :: Dash
Requires-Python: >=3.6.0
License-File: LICENSE
